README.rst
setup.py
pygtaw/__init__.py
pygtaw/langs.py
pygtaw/wrapper.py
pygtaw.egg-info/PKG-INFO
pygtaw.egg-info/SOURCES.txt
pygtaw.egg-info/dependency_links.txt
pygtaw.egg-info/requires.txt
pygtaw.egg-info/top_level.txt