Metadata-Version: 1.0
Name: pygtaw
Version: 0.0.5
Summary: A tiny Google Translate API wrapper written in Python.
Home-page: http://github.com/stephsamson/pygtaw
Author: Steph Samson
Author-email: sdvsamson@gmail.com
License: MIT
Keywords: google translate API wrapper
Platform: UNKNOWN
